napari_simpleannotate/__init__.py
napari_simpleannotate/_bbox_video_widget.py
napari_simpleannotate/_bbox_widget.py
napari_simpleannotate/_labelimg_widget.py
napari_simpleannotate/_utils.py
napari_simpleannotate/napari.yaml
napari_simpleannotate/_tests/__init__.py
napari_simpleannotate/_tests/test_bbox_video_widget.py
napari_simpleannotate/_tests/test_bbox_widget.py
napari_simpleannotate/_tests/test_labelimg_widget.py
napari_simpleannotate/_tests/test_utils.py
napari_simpleannotate/_tests/test_widget.py
napari_simpleannotate-0.1.5.dist-info/licenses/LICENSE
napari_simpleannotate-0.1.5.dist-info/METADATA
napari_simpleannotate-0.1.5.dist-info/WHEEL
napari_simpleannotate-0.1.5.dist-info/entry_points.txt
napari_simpleannotate-0.1.5.dist-info/top_level.txt
napari_simpleannotate-0.1.5.dist-info/RECORD
