Metadata-Version: 2.4
Name: napari-simpleannotate
Version: 0.1.5
Summary: A napari plugin for simple image and video annotation
Author-email: Hiroki Kawai <h.kawai888@gmail.com>
License: BSD-3-Clause
Project-URL: homepage, https://github.com/hiroalchem/napari-simpleannotate
Project-URL: repository, https://github.com/hiroalchem/napari-simpleannotate
Project-URL: documentation, https://github.com/hiroalchem/napari-simpleannotate#README.md
Project-URL: Bug Tracker, https://github.com/hiroalchem/napari-simpleannotate/issues
Project-URL: User Support, https://github.com/hiroalchem/napari-simpleannotate/issues
Classifier: Development Status :: 2 - Pre-Alpha
Classifier: Framework :: napari
Classifier: Intended Audience :: Developers
Classifier: Operating System :: OS Independent
Classifier: Programming Language :: Python
Classifier: Programming Language :: Python :: 3
Classifier: Programming Language :: Python :: 3 :: Only
Classifier: Programming Language :: Python :: 3.8
Classifier: Programming Language :: Python :: 3.9
Classifier: Programming Language :: Python :: 3.10
Classifier: Topic :: Scientific/Engineering :: Image Processing
Requires-Python: >=3.8
License-File: LICENSE
Requires-Dist: numpy
Requires-Dist: magicgui
Requires-Dist: pyyaml
Requires-Dist: qtpy
Requires-Dist: scikit-image
Requires-Dist: pandas
Requires-Dist: napari_video
Requires-Dist: zarr
Requires-Dist: numcodecs
Requires-Dist: opencv-contrib-python
Provides-Extra: testing
Requires-Dist: tox; extra == "testing"
Requires-Dist: pytest; extra == "testing"
Requires-Dist: pytest-cov; extra == "testing"
Requires-Dist: pytest-qt; extra == "testing"
Requires-Dist: napari; extra == "testing"
Requires-Dist: pyqt5; extra == "testing"
Dynamic: license-file
